splaytree_compression/__init__.py
splaytree_compression/__main__.py
splaytree_compression/cli.py
splaytree_compression/compressor.py
splaytree_compression/core.py
splaytree_compression-2.0.0.dist-info/licenses/LICENSE
splaytree_compression-2.0.0.dist-info/METADATA
splaytree_compression-2.0.0.dist-info/WHEEL
splaytree_compression-2.0.0.dist-info/entry_points.txt
splaytree_compression-2.0.0.dist-info/top_level.txt
splaytree_compression-2.0.0.dist-info/RECORD
