Metadata-Version: 2.4
Name: splaytree-compression
Version: 2.0.0
Summary: Lossless compression using adaptive Splay Tree with BWT+MTF pipeline support
Home-page: https://github.com/yourusername/splaytree-compression
Author: Splay Tree Compression Team
Author-email: 
License: MIT
Keywords: compression,splay-tree,lossless,adaptive,prefix-coding
Classifier: Development Status :: 4 - Beta
Classifier: Intended Audience :: Developers
Classifier: Intended Audience :: Science/Research
Classifier: Topic :: System :: Archiving :: Compression
Classifier: Topic :: Scientific/Engineering
Classifier: License :: OSI Approved :: MIT License
Classifier: Programming Language :: Python :: 3
Classifier: Programming Language :: Python :: 3.7
Classifier: Programming Language :: Python :: 3.8
Classifier: Programming Language :: Python :: 3.9
Classifier: Programming Language :: Python :: 3.10
Classifier: Programming Language :: Python :: 3.11
Classifier: Programming Language :: Python :: 3.12
Requires-Python: >=3.7
License-File: LICENSE
Provides-Extra: dev
Requires-Dist: pytest>=6.0; extra == "dev"
Requires-Dist: pytest-cov; extra == "dev"
Requires-Dist: black; extra == "dev"
Requires-Dist: mypy; extra == "dev"
Dynamic: home-page
Dynamic: license-file
Dynamic: requires-python
